hud_sdk/format_utils.py
hud_sdk/logging.py
hud_sdk/config.py
hud_sdk/version.py
hud_sdk/_internal.py
hud_sdk/flow_metrics.py
hud_sdk/run_mode.py
hud_sdk/kafka_declaration_manager.py
hud_sdk/globals.py
hud_sdk/client.py
hud_sdk/hook.py
hud_sdk/__init__.py
hud_sdk/endpoint_manager.py
hud_sdk/auto_hook.py
hud_sdk/exception_handler.py
hud_sdk/forkable.py
hud_sdk/utils.py
hud_sdk/user_options.py
hud_sdk/process_utils.py
hud_sdk/arq_declaration_manager.py
hud_sdk/load.py
hud_sdk/auto_hook_enabled.py
hud_sdk/invocations_handler.py
hud_sdk/json.py
hud_sdk/native.pyi
hud_sdk/user_logs.py
hud_sdk/declarations.py
hud_sdk/investigation_manager.py
hud_sdk/native.cpython-311-darwin.so
hud_sdk/collectors/__init__.py
hud_sdk/collectors/runtime.py
hud_sdk/collectors/modules.py
hud_sdk/collectors/performance.py
hud_sdk/auto_init/hud_entrypoint.py
hud_sdk/auto_init/__init__.py
hud_sdk/auto_init/sitecustomize.py
hud_sdk/auto_init/utils.py
hud_sdk/auto_init/start_hud.py
hud_sdk/schemas/responses.py
hud_sdk/schemas/events.py
hud_sdk/schemas/__init__.py
hud_sdk/schemas/investigation.py
hud_sdk/schemas/requests.py
hud_sdk/schemas/schema.py
hud_sdk/instrumentation/fastapi_instrumentation.py
hud_sdk/instrumentation/aiokafka_instrumentation.py
hud_sdk/instrumentation/apm_trace_ids.py
hud_sdk/instrumentation/arq_instrumentation.py
hud_sdk/instrumentation/runpy_instrumentation.py
hud_sdk/instrumentation/limited_logger.py
hud_sdk/instrumentation/__init__.py
hud_sdk/instrumentation/metaclass.py
hud_sdk/instrumentation/base_instrumentation.py
hud_sdk/instrumentation/starlette_instrumentation.py
hud_sdk/instrumentation/flask_instrumentation.py
hud_sdk/instrumentation/tornado_instrumentation.py
hud_sdk/instrumentation/asyncio_instrumentation.py
hud_sdk/instrumentation/investigation/investigation_thresholds.py
hud_sdk/instrumentation/investigation/triggers.py
hud_sdk/instrumentation/investigation/rate_limiter.py
hud_sdk-0.4.3.dist-info/RECORD
hud_sdk-0.4.3.dist-info/WHEEL
hud_sdk-0.4.3.dist-info/entry_points.txt
hud_sdk-0.4.3.dist-info/top_level.txt
hud_sdk-0.4.3.dist-info/METADATA
hud_sdk-0.4.3.dist-info/licenses/LICENSE
hud_sdk-0.4.3.dist-info/licenses/THIRD_PARTY_LICENSES.txt
