Metadata-Version: 2.4
Name: hud-sdk
Version: 0.4.3
License: **Hud Technology Inc ("Hud") IDE/SDK License**
Requires-Python: >=3.5
License-File: LICENSE
Dynamic: license-file
